LICENSE
MANIFEST.in
README.md
setup.py
odmltools/__init__.py
odmltools/info.json
odmltools/info.py
odmltools.egg-info/PKG-INFO
odmltools.egg-info/SOURCES.txt
odmltools.egg-info/dependency_links.txt
odmltools.egg-info/entry_points.txt
odmltools.egg-info/requires.txt
odmltools.egg-info/top_level.txt
odmltools/importers/__init__.py
odmltools/importers/import_datacite.py
test/test_importers_datacite.py
test/test_importers_datacite_integration.py
test/resources/fullDataCiteSchema.xml
test/resources/fullDataCiteSchemaNS.xml
test/resources/load.xml
test/resources/noxml.md
test/resources/unsupportedNS.xml