Metadata-Version: 2.1
Name: odmltools
Version: 1.0.0
Summary: open metadata Markup Language convenience tools
Home-page: https://github.com/G-Node/odmltools
Author: Michael Sonntag
Author-email: dev@g-node.org
License: BSD
Platform: UNKNOWN
Classifier: Development Status :: 5 - Production/Stable
Classifier: Programming Language :: Python
Classifier: Programming Language :: Python :: 3.6
Classifier: Programming Language :: Python :: 3.7
Classifier: Programming Language :: Python :: 3.8
Classifier: Topic :: Scientific/Engineering
Classifier: Intended Audience :: Science/Research
Classifier: License :: OSI Approved :: BSD License
